eco_connect/__init__.py
eco_connect/facts_service.py
eco_connect-0.24.1.dist-info/LICENSE.txt
eco_connect-0.24.1.dist-info/METADATA
eco_connect-0.24.1.dist-info/RECORD
eco_connect-0.24.1.dist-info/WHEEL
eco_connect-0.24.1.dist-info/top_level.txt
