Metadata-Version: 2.1
Name: eco-connect
Version: 0.24.1
Summary: Ecorithm's connector to Facts Service
Home-page: https://ecorithm.com
Author: Ecorithm
Author-email: support@ecorithm.com
License: MIT
Project-URL: Documentation, http://eco-connect.readthedocs.io/en/latest/
Project-URL: Source Code, https://github.com/ecorithm/eco_connect
Platform: UNKNOWN
Classifier: Development Status :: 5 - Production/Stable
Classifier: Intended Audience :: Developers
Classifier: License :: OSI Approved :: MIT License
Classifier: Natural Language :: English
Classifier: Programming Language :: Python :: 3.6
Classifier: Programming Language :: Python :: 3.7
Classifier: Programming Language :: Python :: 3 :: Only
Classifier: Topic :: Scientific/Engineering
Requires-Python: >=3.6
Provides-Extra: docs
Requires-Dist: pandas
Provides-Extra: docs
Requires-Dist: sphinx; extra == 'docs'
Requires-Dist: sphinx-rtd-theme; extra == 'docs'
